labelbase/__init__.py
labelbase/annotate.py
labelbase/connector.py
labelbase/dataset.py
labelbase/downloader.py
labelbase/masks.py
labelbase/metadata.py
labelbase/models.py
labelbase/ontology.py
labelbase/uploader.py
labelbase/converters/__init__.py
labelbase/converters/coco.py
labelbase-0.1.5.dist-info/LICENSE
labelbase-0.1.5.dist-info/METADATA
labelbase-0.1.5.dist-info/WHEEL
labelbase-0.1.5.dist-info/top_level.txt
labelbase-0.1.5.dist-info/RECORD
