Metadata-Version: 2.1
Name: labelbase
Version: 0.1.5
Summary: Labelbox Helper Library
Home-page: https://labelbox.com
Author: Labelbox
Author-email: raphael@labelbox.com
Keywords: labelbox,labelbase
License-File: LICENSE
Requires-Dist: labelbox[data]
Requires-Dist: packaging
Provides-Extra: dev
Requires-Dist: pylint ; extra == 'dev'
